aanalytics2/CSV_Column_and_Query_String_Reference.pickle
aanalytics2/__init__.py
aanalytics2/__version__.py
aanalytics2/aanalytics14.py
aanalytics2/aanalytics2.py
aanalytics2/annotationCreator.py
aanalytics2/config.py
aanalytics2/configs.py
aanalytics2/connector.py
aanalytics2/datarepair.py
aanalytics2/dwhCreator.py
aanalytics2/eventType_usageLogs.pickle
aanalytics2/ingestion.py
aanalytics2/projects.py
aanalytics2/requestCreator.py
aanalytics2/supported_tags.pickle
aanalytics2/token_provider.py
aanalytics2/workspace.py
aanalytics2-0.4.4.dist-info/licenses/LICENSE
test/__init__.py
test/test_configuration.py
test/test_core_analytics.py
aanalytics2-0.4.4.dist-info/METADATA
aanalytics2-0.4.4.dist-info/WHEEL
aanalytics2-0.4.4.dist-info/top_level.txt
aanalytics2-0.4.4.dist-info/RECORD
