Metadata-Version: 2.4
Name: aanalytics2
Version: 0.4.4
Summary: Adobe Analytics API 2.0 and 1.4 python wrapper
Home-page: https://github.com/pitchmuc/adobe-analytics-api-2.0
Author: Julien Piccini
Author-email: Julien Piccini <piccini.julien@gmail.com>
License: Apache License 2.0
Project-URL: homepage, https://github.com/pitchmuc/adobe-analytics-api-2.0
Project-URL: changelog, https://github.com/pitchmuc/adobe-analytics-api-2.0/blob/master/docs/releases.md
Keywords: adobe,analytics,API,python
Classifier: Intended Audience :: Developers
Classifier: License :: OSI Approved :: GNU General Public License v3 (GPLv3)
Classifier: Operating System :: OS Independent
Classifier: Programming Language :: Python
Classifier: Topic :: Scientific/Engineering :: Information Analysis
Classifier: Programming Language :: Python :: 3.6
Classifier: Programming Language :: Python :: 3.7
Classifier: Programming Language :: Python :: 3.8
Classifier: Programming Language :: Python :: 3.9
Classifier: Development Status :: 4 - Beta
Requires-Python: >=3.6
License-File: LICENSE
Requires-Dist: pandas>=0.25.3
Requires-Dist: pathlib2
Requires-Dist: pathlib
Requires-Dist: requests
Requires-Dist: PyJWT[crypto]
Requires-Dist: PyJWT
Requires-Dist: dicttoxml
Requires-Dist: pytest
Requires-Dist: openpyxl>2.6.0
Provides-Extra: dynamic
Requires-Dist: version; extra == "dynamic"
Dynamic: author
Dynamic: home-page
Dynamic: license-file
Dynamic: requires-python
